steamboat/__init__.py
steamboat/core/__init__.py
steamboat/core/connection.py
steamboat/core/exceptions.py
steamboat/core/result.py
steamboat/core/runner.py
steamboat/core/step.py
steamboat/extras/__init__.py
steamboat/extras/dataframe_extras.py
steamboat/extras/xml_extras.py
tests/__init__.py
tests/conftest.py
tests/test_result.py
tests/test_runner.py
tests/test_step.py
steamboat-0.1.5.dist-info/METADATA
steamboat-0.1.5.dist-info/WHEEL
steamboat-0.1.5.dist-info/top_level.txt
steamboat-0.1.5.dist-info/RECORD
