Metadata-Version: 2.1
Name: steamboat
Version: 0.1.5
Summary: DAG oriented data pipeline task orchestrator
Home-page: https://github.com/ghukill/steamboat
Author: Graham Hukill
Author-email: ghukill@gmail.com
Requires-Dist: attrs >=23.1.0
Requires-Dist: mypy >=1.5.1
Requires-Dist: networkx >=3.1
Requires-Dist: networkx-stubs >=0.0.1
Provides-Extra: dataframe
Requires-Dist: duckdb >=0.8.1 ; extra == 'dataframe'
Requires-Dist: pandas >=2.0.3 ; extra == 'dataframe'
Provides-Extra: xml
Requires-Dist: lxml >=4.9.0 ; extra == 'xml'
